SECURITY.md
certbot_dns_myracloud/__init__.py
certbot_dns_myracloud/myracloud.py
certbot_dns_myracloud-0.1.2.dist-info/LICENSE
certbot_dns_myracloud-0.1.2.dist-info/METADATA
certbot_dns_myracloud-0.1.2.dist-info/WHEEL
certbot_dns_myracloud-0.1.2.dist-info/entry_points.txt
certbot_dns_myracloud-0.1.2.dist-info/RECORD
